jsonmodule/__init__.py
jsonmodule/jsonimporter.py
json_like_module-0.0.1.dist-info/METADATA
json_like_module-0.0.1.dist-info/WHEEL
json_like_module-0.0.1.dist-info/top_level.txt
json_like_module-0.0.1.dist-info/RECORD
